napper-0.1a1.dist-info/METADATA
napper-0.1a1.dist-info/WHEEL
napper-0.1a1.dist-info/RECORD
napper-0.1a1.dist-info/DESCRIPTION.rst
napper-0.1a1.dist-info/top_level.txt
napper-0.1a1.dist-info/metadata.json
napper/apis.py
napper/errors.py
napper/util.py
napper/response.py
napper/__init__.py
napper/request.py
napper/tests/test_request.py
napper/tests/util.py
napper/tests/test_site.py
napper/tests/__init__.py
napper/tests/test_json.py
