Metadata-Version: 2.0
Name: napper
Version: 0.1a1
Summary: A REST client for Python
Home-page: https://github.com/epsy/napper
Author: Yann Kaiser
Author-email: kaiser.yann@gmail.com
License: MIT
Keywords: http,requests,api,asyncio,asynchronous
Platform: UNKNOWN
Classifier: Development Status :: 3 - Alpha
Classifier: License :: OSI Approved :: MIT License
Classifier: Programming Language :: Python :: 3.5
Classifier: Intended Audience :: Developers
Classifier: Intended Audience :: Information Technology
Classifier: Intended Audience :: Science/Research
Classifier: Intended Audience :: System Administrators
Classifier: Operating System :: OS Independent
Classifier: Topic :: Internet :: WWW/HTTP
Requires-Dist: aiohttp
